SwooleZhongwenWendang/README.md
SwooleZhongwenWendang/__init__.py
SwooleZhongwenWendang/__main__.py
SwooleZhongwenWendang/file.epub
SwooleZhongwenWendang/index.html
SwooleZhongwenWendang/css/__init__.py
SwooleZhongwenWendang/css/annotations.css
SwooleZhongwenWendang/css/main.css
SwooleZhongwenWendang/css/normalize.css
SwooleZhongwenWendang/css/popup.css
SwooleZhongwenWendang/font/__init__.py
SwooleZhongwenWendang/font/fontello.eot
SwooleZhongwenWendang/font/fontello.svg
SwooleZhongwenWendang/font/fontello.ttf
SwooleZhongwenWendang/font/fontello.woff
SwooleZhongwenWendang/img/__init__.py
SwooleZhongwenWendang/img/annotator-glyph-sprite.png
SwooleZhongwenWendang/img/annotator-icon-sprite.png
SwooleZhongwenWendang/img/apple-touch-icon.png
SwooleZhongwenWendang/img/cancelfullscreen.png
SwooleZhongwenWendang/img/close.png
SwooleZhongwenWendang/img/fullscreen.png
SwooleZhongwenWendang/img/loader.gif
SwooleZhongwenWendang/img/menu-icon.png
SwooleZhongwenWendang/img/save.png
SwooleZhongwenWendang/img/saved.png
SwooleZhongwenWendang/img/settings-s.png
SwooleZhongwenWendang/img/settings.png
SwooleZhongwenWendang/img/star.png
SwooleZhongwenWendang/js/__init__.py
SwooleZhongwenWendang/js/epub.js
SwooleZhongwenWendang/js/epub.min.js
SwooleZhongwenWendang/js/epub.min.map
SwooleZhongwenWendang/js/hooks.min.js
SwooleZhongwenWendang/js/hooks.min.map
SwooleZhongwenWendang/js/reader.js
SwooleZhongwenWendang/js/reader.js.map
SwooleZhongwenWendang/js/reader.min.js
SwooleZhongwenWendang/js/reader.min.map
SwooleZhongwenWendang/js/hooks/__init__.py
SwooleZhongwenWendang/js/hooks/extensions/__init__.py
SwooleZhongwenWendang/js/hooks/extensions/highlight.js
SwooleZhongwenWendang/js/libs/__init__.py
SwooleZhongwenWendang/js/libs/jquery.min.js
SwooleZhongwenWendang/js/libs/localforage.min.js
SwooleZhongwenWendang/js/libs/screenfull.js
SwooleZhongwenWendang/js/libs/screenfull.min.js
SwooleZhongwenWendang/js/libs/zip.min.js
SwooleZhongwenWendang/js/plugins/__init__.py
swoole_zhongwen_wendang-2024.3.2.0.dist-info/METADATA
swoole_zhongwen_wendang-2024.3.2.0.dist-info/WHEEL
swoole_zhongwen_wendang-2024.3.2.0.dist-info/entry_points.txt
swoole_zhongwen_wendang-2024.3.2.0.dist-info/top_level.txt
swoole_zhongwen_wendang-2024.3.2.0.dist-info/RECORD
